trianglengin-2.0.7.dist-info/WHEEL
trianglengin-2.0.7.dist-info/RECORD
trianglengin-2.0.7.dist-info/top_level.txt
trianglengin-2.0.7.dist-info/entry_points.txt
trianglengin-2.0.7.dist-info/METADATA
trianglengin-2.0.7.dist-info/licenses/LICENSE
trianglengin.libs/libgcc_s-f3fb5a36.so.1
trianglengin.libs/libstdc++-d2a021ba.so.6.0.32
trianglengin/trianglengin_cpp.cpython-37m-i386-linux-gnu.so
trianglengin/trianglengin_cpp.cpython-310-i386-linux-gnu.so
trianglengin/game_interface.py
trianglengin/py.typed
trianglengin/__init__.py
trianglengin/config/README.md
trianglengin/config/env_config.py
trianglengin/config/display_config.py
trianglengin/config/__init__.py
trianglengin/cpp/game_state.cpp
trianglengin/cpp/structs.h
trianglengin/cpp/grid_data.cpp
trianglengin/cpp/grid_logic.h
trianglengin/cpp/grid_logic.cpp
trianglengin/cpp/bindings.cpp
trianglengin/cpp/shape_logic.h
trianglengin/cpp/config.h
trianglengin/cpp/grid_data.h
trianglengin/cpp/game_state.h
trianglengin/cpp/shape_logic.cpp
trianglengin/cpp/CMakeLists.txt
trianglengin/utils/geometry.py
trianglengin/utils/__init__.py
trianglengin/utils/types.py
trianglengin/ui/README.md
trianglengin/ui/app.py
trianglengin/ui/config.py
trianglengin/ui/__init__.py
trianglengin/ui/cli.py
trianglengin/ui/interaction/debug_mode_handler.py
trianglengin/ui/interaction/play_mode_handler.py
trianglengin/ui/interaction/README.md
trianglengin/ui/interaction/event_processor.py
trianglengin/ui/interaction/__init__.py
trianglengin/ui/interaction/input_handler.py
trianglengin/ui/visualization/README.md
trianglengin/ui/visualization/__init__.py
trianglengin/ui/visualization/drawing/README.md
trianglengin/ui/visualization/drawing/highlight.py
trianglengin/ui/visualization/drawing/shapes.py
trianglengin/ui/visualization/drawing/hud.py
trianglengin/ui/visualization/drawing/grid.py
trianglengin/ui/visualization/drawing/utils.py
trianglengin/ui/visualization/drawing/__init__.py
trianglengin/ui/visualization/drawing/previews.py
trianglengin/ui/visualization/core/colors.py
trianglengin/ui/visualization/core/layout.py
trianglengin/ui/visualization/core/README.md
trianglengin/ui/visualization/core/coord_mapper.py
