Metadata-Version: 2.4
Name: trianglengin
Version: 2.0.7
Summary: High-performance C++/Python engine for a triangle puzzle game.
Author-email: "Luis Guilherme P. M." <lgpelin92@gmail.com>
License-Expression: MIT
Project-URL: Homepage, https://github.com/lguibr/trianglengin
Project-URL: Bug Tracker, https://github.com/lguibr/trianglengin/issues
Classifier: Programming Language :: Python :: 3
Classifier: Programming Language :: Python :: 3.10
Classifier: Programming Language :: Python :: 3.11
Classifier: Programming Language :: C++
Classifier: Operating System :: OS Independent
Classifier: Topic :: Scientific/Engineering :: Artificial Intelligence
Classifier: Topic :: Games/Entertainment :: Puzzle Games
Classifier: Development Status :: 4 - Beta
Requires-Python: >=3.10
License-File: LICENSE
Requires-Dist: numpy>=1.20.0
Requires-Dist: pydantic>=2.0.0
Requires-Dist: typing_extensions>=4.0.0
Requires-Dist: pygame>=2.1.0
Requires-Dist: typer[all]>=0.9.0
Provides-Extra: dev
Requires-Dist: pytest>=7.0.0; extra == "dev"
Requires-Dist: pytest-cov>=3.0.0; extra == "dev"
Requires-Dist: pytest-mock>=3.0.0; extra == "dev"
Requires-Dist: ruff; extra == "dev"
Requires-Dist: mypy; extra == "dev"
Requires-Dist: build; extra == "dev"
Requires-Dist: twine; extra == "dev"
Requires-Dist: codecov; extra == "dev"
Dynamic: license-file
